s3pact/s3pact.py
s3pact-0.1.3.data/scripts/s3pact.py
s3pact-0.1.3.dist-info/METADATA
s3pact-0.1.3.dist-info/WHEEL
s3pact-0.1.3.dist-info/top_level.txt
s3pact-0.1.3.dist-info/RECORD
