Metadata-Version: 2.1
Name: s3pact
Version: 0.1.3
Summary: S3 Parallel ACtion
Home-page: https://github.com/mello7tre/S3PAct
Author: Mello
Author-email: mello+python@ankot.org
License: OSI Approved :: Open Software License 3.0 (OSL-3.0)
Classifier: Programming Language :: Python :: 3
Classifier: License :: OSI Approved :: Open Software License 3.0 (OSL-3.0)
Classifier: Operating System :: OS Independent
Requires-Python: >=3.9
Requires-Dist: boto3
